cruds_adminlte/__init__.py
cruds_adminlte/crud.py
cruds_adminlte/filter.py
cruds_adminlte/inline_crud.py
cruds_adminlte/models.py
cruds_adminlte/urls.py
cruds_adminlte/utils.py
cruds_adminlte/views.py
cruds_adminlte/widgets.py
cruds_adminlte/static/admin-lte/dist/css/AdminLTE.css
cruds_adminlte/static/admin-lte/dist/css/AdminLTE.min.css
cruds_adminlte/static/admin-lte/dist/css/adminlte.css.map
cruds_adminlte/static/admin-lte/dist/css/adminlte.min.css.map
cruds_adminlte/static/admin-lte/dist/css/alt/AdminLTE-bootstrap-social.css
cruds_adminlte/static/admin-lte/dist/css/alt/AdminLTE-bootstrap-social.min.css
cruds_adminlte/static/admin-lte/dist/css/alt/AdminLTE-fullcalendar.css
cruds_adminlte/static/admin-lte/dist/css/alt/AdminLTE-fullcalendar.min.css
cruds_adminlte/static/admin-lte/dist/css/alt/AdminLTE-select2.css
cruds_adminlte/static/admin-lte/dist/css/alt/AdminLTE-select2.min.css
cruds_adminlte/static/admin-lte/dist/css/alt/AdminLTE-without-plugins.css
cruds_adminlte/static/admin-lte/dist/css/alt/AdminLTE-without-plugins.min.css
cruds_adminlte/static/admin-lte/dist/css/skins/_all-skins.css
cruds_adminlte/static/admin-lte/dist/css/skins/_all-skins.min.css
cruds_adminlte/static/admin-lte/dist/css/skins/skin-black-light.css
cruds_adminlte/static/admin-lte/dist/css/skins/skin-black-light.min.css
cruds_adminlte/static/admin-lte/dist/css/skins/skin-black.css
cruds_adminlte/static/admin-lte/dist/css/skins/skin-black.min.css
cruds_adminlte/static/admin-lte/dist/css/skins/skin-blue-light.css
cruds_adminlte/static/admin-lte/dist/css/skins/skin-blue-light.min.css
cruds_adminlte/static/admin-lte/dist/css/skins/skin-blue.css
cruds_adminlte/static/admin-lte/dist/css/skins/skin-blue.min.css
cruds_adminlte/static/admin-lte/dist/css/skins/skin-green-light.css
cruds_adminlte/static/admin-lte/dist/css/skins/skin-green-light.min.css
cruds_adminlte/static/admin-lte/dist/css/skins/skin-green.css
django_cruds_padminlte-0.0.13a5.dist-info/METADATA
django_cruds_padminlte-0.0.13a5.dist-info/RECORD
django_cruds_padminlte-0.0.13a5.dist-info/WHEEL
django_cruds_padminlte-0.0.13a5.dist-info/top_level.txt
