Metadata-Version: 2.1
Name: django-cruds-padminlte
Version: 0.0.13a5
Summary: django-cruds-adminlte is simple drop-in django app that creates CRUD for faster prototyping.
Home-page: https://github.com/oscarmlage/django-cruds-adminlte
Author: Óscar M. Lage
Author-email: info@oscarmlage.com
License: BSD
Keywords: django-cruds-adminlte
Platform: UNKNOWN
Classifier: Development Status :: 2 - Pre-Alpha
Classifier: Framework :: Django
Classifier: Intended Audience :: Developers
Classifier: License :: OSI Approved :: BSD License
Classifier: Natural Language :: English
Classifier: Programming Language :: Python :: 2
Classifier: Programming Language :: Python :: 2.6
Classifier: Programming Language :: Python :: 2.7
Classifier: Programming Language :: Python :: 3
Classifier: Programming Language :: Python :: 3.3
Requires-Dist: django-crispy-forms
Requires-Dist: djangoajax
